{
  "key": "13101045_13101045",
  "title": "不删/不刪  Bu Shan",
  "artist": "井胧/井朧",
  "arranger": "_Nihao",
  "web_url": "https://www.smule.com/song/arr/13101045_13101045",
  "cover_url": "https://c-cf.cdn.smule.com/rs-s-sf-3/arr/42/a5/673e17da-627f-4919-b4c0-c8ec302d031b.jpg",
  "has_lyrics": true,
  "line_count": 102,
  "lyric_line_count": 70,
  "lines": [
    {
      "raw": "不删 - 井胧",
      "chinese": "不删 - 井胧",
      "pinyin": "",
      "type": "chinese-only"
    },
    {
      "raw": "",
      "chinese": "",
      "pinyin": "",
      "type": "blank"
    },
    {
      "raw": "作词 ：闫骁男",
      "chinese": "作词 ：闫骁男",
      "pinyin": "",
      "type": "chinese-only"
    },
    {
      "raw": "作曲 ：闫骁男/张娉言",
      "chinese": "作曲 ：闫骁男/张娉言",
      "pinyin": "",
      "type": "chinese-only"
    },
    {
      "raw": "编曲 ：姚瀚霄@骁Studio",
      "chinese": "编曲 ：姚瀚霄@骁",
      "pinyin": "Studio",
      "type": "lyric"
    },
    {
      "raw": "制作人 ：闫骁男@骁Studio",
      "chinese": "制作人 ：闫骁男@骁",
      "pinyin": "Studio",
      "type": "lyric"
    },
    {
      "raw": "出品 ： 星巢骁盛（骁Studio)",
      "chinese": "出品 ： 星巢骁盛（骁",
      "pinyin": "Studio)",
      "type": "lyric"
    },
    {
      "raw": "",
      "chinese": "",
      "pinyin": "",
      "type": "blank"
    },
    {
      "raw": "得不到的 dé bù dào de",
      "chinese": "得不到的",
      "pinyin": "dé bù dào de",
      "type": "lyric"
    },
    {
      "raw": "忘不掉的 wàng bù diào de",
      "chinese": "忘不掉的",
      "pinyin": "wàng bù diào de",
      "type": "lyric"
    },
    {
      "raw": "改不了的 gǎi bù liǎo de",
      "chinese": "改不了的",
      "pinyin": "gǎi bù liǎo de",
      "type": "lyric"
    },
    {
      "raw": "解不开的 结果 jiě bù kāi de jié guǒ",
      "chinese": "解不开的 结果",
      "pinyin": "jiě bù kāi de jié guǒ",
      "type": "lyric"
    },
    {
      "raw": "放不下的 fàng bù xià de",
      "chinese": "放不下的",
      "pinyin": "fàng bù xià de",
      "type": "lyric"
    },
    {
      "raw": "留不住的 liú bù zhù de",
      "chinese": "留不住的",
      "pinyin": "liú bù zhù de",
      "type": "lyric"
    },
    {
      "raw": "最亲爱的 那个 zuì qīn ài de nà gè",
      "chinese": "最亲爱的 那个",
      "pinyin": "zuì qīn ài de nà gè",
      "type": "lyric"
    },
    {
      "raw": "",
      "chinese": "",
      "pinyin": "",
      "type": "blank"
    },
    {
      "raw": "犯了什么 错 fàn le shén me cuò",
      "chinese": "犯了什么 错",
      "pinyin": "fàn le shén me cuò",
      "type": "lyric"
    },
    {
      "raw": "着了谁的 魔 zhāo le shéi de mó",
      "chinese": "着了谁的 魔",
      "pinyin": "zhāo le shéi de mó",
      "type": "lyric"
    },
    {
      "raw": "唱了这首 歌 chàng le zhè shǒu gē",
      "chinese": "唱了这首 歌",
      "pinyin": "chàng le zhè shǒu gē",
      "type": "lyric"
    },
    {
      "raw": "无奈还剩 许多 wú nài hái shèng xǔ duō",
      "chinese": "无奈还剩 许多",
      "pinyin": "wú nài hái shèng xǔ duō",
      "type": "lyric"
    },
    {
      "raw": "在回忆的 王国 zài huí yì de wáng guó",
      "chinese": "在回忆的 王国",
      "pinyin": "zài huí yì de wáng guó",
      "type": "lyric"
    },
    {
      "raw": "坐寂寞的 宝座 zuò jì mò de bǎo zuò",
      "chinese": "坐寂寞的 宝座",
      "pinyin": "zuò jì mò de bǎo zuò",
      "type": "lyric"
    },
    {
      "raw": "等时间来 解脱 děng shí jiān lái jiě tuō",
      "chinese": "等时间来 解脱",
      "pinyin": "děng shí jiān lái jiě tuō",
      "type": "lyric"
    },
    {
      "raw": "",
      "chinese": "",
      "pinyin": "",
      "type": "blank"
    },
    {
      "raw": "",
      "chinese": "",
      "pinyin": "",
      "type": "blank"
    },
    {
      "raw": "为什么留着你的 wèi shén me liú zhe nǐ de",
      "chinese": "为什么留着你的",
      "pinyin": "wèi shén me liú zhe nǐ de",
      "type": "lyric"
    },
    {
      "raw": "",
      "chinese": "",
      "pinyin": "",
      "type": "blank"
    },
    {
      "raw": "微信不删 wéi xìn bù shān",
      "chinese": "微信不删",
      "pinyin": "wéi xìn bù shān",
      "type": "lyric"
    },
    {
      "raw": "为什么当初说好 wèi shén me dāng chū shuō hǎo",
      "chinese": "为什么当初说好",
      "pinyin": "wèi shén me dāng chū shuō hǎo",
      "type": "lyric"
    },
    {
      "raw": "的话不算 de huà bù suàn",
      "chinese": "的话不算",
      "pinyin": "de huà bù suàn",
      "type": "lyric"
    },
    {
      "raw": "既然都已经决定 jì rán dōu yǐ jīng jué dìng",
      "chinese": "既然都已经决定",
      "pinyin": "jì rán dōu yǐ jīng jué dìng",
      "type": "lyric"
    },
    {
      "raw": "一刀两断 yī dāo liǎng duàn",
      "chinese": "一刀两断",
      "pinyin": "yī dāo liǎng duàn",
      "type": "lyric"
    },
    {
      "raw": "曾经的习惯还是 céng jīng de xí guàn hái shì",
      "chinese": "曾经的习惯还是",
      "pinyin": "céng jīng de xí guàn hái shì",
      "type": "lyric"
    },
    {
      "raw": "留了一半 liú le yī bàn",
      "chinese": "留了一半",
      "pinyin": "liú le yī bàn",
      "type": "lyric"
    },
    {
      "raw": "",
      "chinese": "",
      "pinyin": "",
      "type": "blank"
    },
    {
      "raw": "",
      "chinese": "",
      "pinyin": "",
      "type": "blank"
    },
    {
      "raw": "今天的你是幸福 jīn tiān de nǐ shì xìng fú",
      "chinese": "今天的你是幸福",
      "pinyin": "jīn tiān de nǐ shì xìng fú",
      "type": "lyric"
    },
    {
      "raw": "",
      "chinese": "",
      "pinyin": "",
      "type": "blank"
    },
    {
      "raw": "还是孤单 hái shì gū dān",
      "chinese": "还是孤单",
      "pinyin": "hái shì gū dān",
      "type": "lyric"
    },
    {
      "raw": "有没有人替我说 yǒu méi yǒu rén tì wǒ shuō",
      "chinese": "有没有人替我说",
      "pinyin": "yǒu méi yǒu rén tì wǒ shuō",
      "type": "lyric"
    },
    {
      "raw": "那句晚安 nà jù wǎn ān",
      "chinese": "那句晚安",
      "pinyin": "nà jù wǎn ān",
      "type": "lyric"
    },
    {
      "raw": "一万个秘密正在 yī wàn gè mì mì zhèng zài",
      "chinese": "一万个秘密正在",
      "pinyin": "yī wàn gè mì mì zhèng zài",
      "type": "lyric"
    },
    {
      "raw": "心底腐烂 xīn dǐ fǔ làn",
      "chinese": "心底腐烂",
      "pinyin": "xīn dǐ fǔ làn",
      "type": "lyric"
    },
    {
      "raw": "不如继续纠缠再 bù rú jì xù jiū chán zài",
      "chinese": "不如继续纠缠再",
      "pinyin": "bù rú jì xù jiū chán zài",
      "type": "lyric"
    },
    {
      "raw": "",
      "chinese": "",
      "pinyin": "",
      "type": "blank"
    },
    {
      "raw": "把故事讲完 bǎ gù shì jiǎng wán",
      "chinese": "把故事讲完",
      "pinyin": "bǎ gù shì jiǎng wán",
      "type": "lyric"
    },
    {
      "raw": "",
      "chinese": "",
      "pinyin": "",
      "type": "blank"
    },
    {
      "raw": "🎸🎶🎸🎶🎸🎶🎸",
      "chinese": "🎸🎶🎸🎶🎸🎶🎸",
      "pinyin": "",
      "type": "chinese-only"
    },
    {
      "raw": "",
      "chinese": "",
      "pinyin": "",
      "type": "blank"
    },
    {
      "raw": "犯了什么 错 fàn le shén me cuò",
      "chinese": "犯了什么 错",
      "pinyin": "fàn le shén me cuò",
      "type": "lyric"
    },
    {
      "raw": "着了谁的 魔 zhāo le shéi de mó",
      "chinese": "着了谁的 魔",
      "pinyin": "zhāo le shéi de mó",
      "type": "lyric"
    },
    {
      "raw": "唱了这首 歌 chàng le zhè shǒu gē",
      "chinese": "唱了这首 歌",
      "pinyin": "chàng le zhè shǒu gē",
      "type": "lyric"
    },
    {
      "raw": "无奈还剩 许多 wú nài hái shèng xǔ duō",
      "chinese": "无奈还剩 许多",
      "pinyin": "wú nài hái shèng xǔ duō",
      "type": "lyric"
    },
    {
      "raw": "在回忆的 王国 zài huí yì de wáng guó",
      "chinese": "在回忆的 王国",
      "pinyin": "zài huí yì de wáng guó",
      "type": "lyric"
    },
    {
      "raw": "坐寂寞的 宝座 zuò jì mò de bǎo zuò",
      "chinese": "坐寂寞的 宝座",
      "pinyin": "zuò jì mò de bǎo zuò",
      "type": "lyric"
    },
    {
      "raw": "等时间来 解脱 děng shí jiān lái jiě tuō",
      "chinese": "等时间来 解脱",
      "pinyin": "děng shí jiān lái jiě tuō",
      "type": "lyric"
    },
    {
      "raw": "",
      "chinese": "",
      "pinyin": "",
      "type": "blank"
    },
    {
      "raw": "",
      "chinese": "",
      "pinyin": "",
      "type": "blank"
    },
    {
      "raw": "为什么留着你的 wèi shén me liú zhe nǐ de",
      "chinese": "为什么留着你的",
      "pinyin": "wèi shén me liú zhe nǐ de",
      "type": "lyric"
    },
    {
      "raw": "",
      "chinese": "",
      "pinyin": "",
      "type": "blank"
    },
    {
      "raw": "微信不删 wéi xìn bù shān",
      "chinese": "微信不删",
      "pinyin": "wéi xìn bù shān",
      "type": "lyric"
    },
    {
      "raw": "为什么当初说好 wèi shén me dāng chū shuō hǎo",
      "chinese": "为什么当初说好",
      "pinyin": "wèi shén me dāng chū shuō hǎo",
      "type": "lyric"
    },
    {
      "raw": "的话不算 de huà bù suàn",
      "chinese": "的话不算",
      "pinyin": "de huà bù suàn",
      "type": "lyric"
    },
    {
      "raw": "既然都已经决定 jì rán dōu yǐ jīng jué dìng",
      "chinese": "既然都已经决定",
      "pinyin": "jì rán dōu yǐ jīng jué dìng",
      "type": "lyric"
    },
    {
      "raw": "一刀两断 yī dāo liǎng duàn",
      "chinese": "一刀两断",
      "pinyin": "yī dāo liǎng duàn",
      "type": "lyric"
    },
    {
      "raw": "曾经的习惯还是 céng jīng de xí guàn hái shì",
      "chinese": "曾经的习惯还是",
      "pinyin": "céng jīng de xí guàn hái shì",
      "type": "lyric"
    },
    {
      "raw": "留了一半 liú le yī bàn",
      "chinese": "留了一半",
      "pinyin": "liú le yī bàn",
      "type": "lyric"
    },
    {
      "raw": "",
      "chinese": "",
      "pinyin": "",
      "type": "blank"
    },
    {
      "raw": "",
      "chinese": "",
      "pinyin": "",
      "type": "blank"
    },
    {
      "raw": "今天的你是幸福 jīn tiān de nǐ shì xìng fú",
      "chinese": "今天的你是幸福",
      "pinyin": "jīn tiān de nǐ shì xìng fú",
      "type": "lyric"
    },
    {
      "raw": "",
      "chinese": "",
      "pinyin": "",
      "type": "blank"
    },
    {
      "raw": "还是孤单 hái shì gū dān",
      "chinese": "还是孤单",
      "pinyin": "hái shì gū dān",
      "type": "lyric"
    },
    {
      "raw": "有没有人替我说 yǒu méi yǒu rén tì wǒ shuō",
      "chinese": "有没有人替我说",
      "pinyin": "yǒu méi yǒu rén tì wǒ shuō",
      "type": "lyric"
    },
    {
      "raw": "那句晚安 nà jù wǎn ān",
      "chinese": "那句晚安",
      "pinyin": "nà jù wǎn ān",
      "type": "lyric"
    },
    {
      "raw": "一万个秘密正在 yī wàn gè mì mì zhèng zài",
      "chinese": "一万个秘密正在",
      "pinyin": "yī wàn gè mì mì zhèng zài",
      "type": "lyric"
    },
    {
      "raw": "心底腐烂 xīn dǐ fǔ làn",
      "chinese": "心底腐烂",
      "pinyin": "xīn dǐ fǔ làn",
      "type": "lyric"
    },
    {
      "raw": "不如继续纠缠再 bù rú jì xù jiū chán zài",
      "chinese": "不如继续纠缠再",
      "pinyin": "bù rú jì xù jiū chán zài",
      "type": "lyric"
    },
    {
      "raw": "把故事讲完 bǎ gù shì jiǎng wán",
      "chinese": "把故事讲完",
      "pinyin": "bǎ gù shì jiǎng wán",
      "type": "lyric"
    },
    {
      "raw": "",
      "chinese": "",
      "pinyin": "",
      "type": "blank"
    },
    {
      "raw": "",
      "chinese": "",
      "pinyin": "",
      "type": "blank"
    },
    {
      "raw": "唱着你的黄昏 chàng zhe nǐ de huáng hūn",
      "chinese": "唱着你的黄昏",
      "pinyin": "chàng zhe nǐ de huáng hūn",
      "type": "lyric"
    },
    {
      "raw": "",
      "chinese": "",
      "pinyin": "",
      "type": "blank"
    },
    {
      "raw": "怪自己的凌晨 guài zì jǐ de líng chén",
      "chinese": "怪自己的凌晨",
      "pinyin": "guài zì jǐ de líng chén",
      "type": "lyric"
    },
    {
      "raw": "回不回得去的我们 huí bù huí dé qù de wǒ men",
      "chinese": "回不回得去的我们",
      "pinyin": "huí bù huí dé qù de wǒ men",
      "type": "lyric"
    },
    {
      "raw": "",
      "chinese": "",
      "pinyin": "",
      "type": "blank"
    },
    {
      "raw": "还没回答的问 hái méi huí dá de wèn",
      "chinese": "还没回答的问",
      "pinyin": "hái méi huí dá de wèn",
      "type": "lyric"
    },
    {
      "raw": "谁伤了谁的魂 shéi shāng le shéi de hún",
      "chinese": "谁伤了谁的魂",
      "pinyin": "shéi shāng le shéi de hún",
      "type": "lyric"
    },
    {
      "raw": "参不透的缘分 cān bù tòu de yuán fèn",
      "chinese": "参不透的缘分",
      "pinyin": "cān bù tòu de yuán fèn",
      "type": "lyric"
    },
    {
      "raw": "",
      "chinese": "",
      "pinyin": "",
      "type": "blank"
    },
    {
      "raw": "",
      "chinese": "",
      "pinyin": "",
      "type": "blank"
    },
    {
      "raw": "今天的你是幸福 jīn tiān de nǐ shì xìng fú",
      "chinese": "今天的你是幸福",
      "pinyin": "jīn tiān de nǐ shì xìng fú",
      "type": "lyric"
    },
    {
      "raw": "",
      "chinese": "",
      "pinyin": "",
      "type": "blank"
    },
    {
      "raw": "还是孤单 hái shì gū dān",
      "chinese": "还是孤单",
      "pinyin": "hái shì gū dān",
      "type": "lyric"
    },
    {
      "raw": "有没有人替我说 yǒu méi yǒu rén tì wǒ shuō",
      "chinese": "有没有人替我说",
      "pinyin": "yǒu méi yǒu rén tì wǒ shuō",
      "type": "lyric"
    },
    {
      "raw": "那句晚安 nà jù wǎn ān",
      "chinese": "那句晚安",
      "pinyin": "nà jù wǎn ān",
      "type": "lyric"
    },
    {
      "raw": "一万个秘密正在 yī wàn gè mì mì zhèng zài",
      "chinese": "一万个秘密正在",
      "pinyin": "yī wàn gè mì mì zhèng zài",
      "type": "lyric"
    },
    {
      "raw": "心底腐烂 xīn dǐ fǔ làn",
      "chinese": "心底腐烂",
      "pinyin": "xīn dǐ fǔ làn",
      "type": "lyric"
    },
    {
      "raw": "不如继续纠缠再 bù rú jì xù jiū chán zài",
      "chinese": "不如继续纠缠再",
      "pinyin": "bù rú jì xù jiū chán zài",
      "type": "lyric"
    },
    {
      "raw": "",
      "chinese": "",
      "pinyin": "",
      "type": "blank"
    },
    {
      "raw": "把故事讲完 bǎ gù shì jiǎng wán",
      "chinese": "把故事讲完",
      "pinyin": "bǎ gù shì jiǎng wán",
      "type": "lyric"
    },
    {
      "raw": "",
      "chinese": "",
      "pinyin": "",
      "type": "blank"
    },
    {
      "raw": "谢谢",
      "chinese": "谢谢",
      "pinyin": "",
      "type": "chinese-only"
    }
  ]
}